shipspy/__init__.py
shipspy/__main__.py
shipspy/_version.py
shipspy/cli.py
shipspy/dship.py
shipspy/helpers.py
shipspy/pamos.py
shipspy/rename.py
shipspy/sections.py
shipspy-1.1.0.dist-info/licenses/LICENCE
shipspy-1.1.0.dist-info/METADATA
shipspy-1.1.0.dist-info/WHEEL
shipspy-1.1.0.dist-info/entry_points.txt
shipspy-1.1.0.dist-info/top_level.txt
shipspy-1.1.0.dist-info/RECORD
