Metadata-Version: 2.4
Name: shipspy
Version: 1.1.0
Summary: processing of ship campaign data
Author-email: Laura Köhler <laura.koehler@awi.de>
License-File: LICENCE
Requires-Dist: xarray
Requires-Dist: numpy
Requires-Dist: metpy
Requires-Dist: scipy
Requires-Dist: pyyaml
Requires-Dist: netcdf4
Requires-Dist: datetime
Requires-Dist: dask
Requires-Dist: pint_xarray
Provides-Extra: tests
Requires-Dist: pytest; extra == "tests"
Requires-Dist: black; extra == "tests"
Dynamic: license-file
